odoo8_addon_hr_security-8.0.1.0.0.99.dev8-py2.7-nspkg.pth
odoo8_addon_hr_security-8.0.1.0.0.99.dev8.dist-info/DESCRIPTION.rst
odoo8_addon_hr_security-8.0.1.0.0.99.dev8.dist-info/METADATA
odoo8_addon_hr_security-8.0.1.0.0.99.dev8.dist-info/RECORD
odoo8_addon_hr_security-8.0.1.0.0.99.dev8.dist-info/WHEEL
odoo8_addon_hr_security-8.0.1.0.0.99.dev8.dist-info/metadata.json
odoo8_addon_hr_security-8.0.1.0.0.99.dev8.dist-info/namespace_packages.txt
odoo8_addon_hr_security-8.0.1.0.0.99.dev8.dist-info/top_level.txt
odoo_addons/hr_security/README.rst
odoo_addons/hr_security/__init__.py
odoo_addons/hr_security/__openerp__.py
odoo_addons/hr_security/i18n/de.po
odoo_addons/hr_security/i18n/es.po
odoo_addons/hr_security/i18n/fr.po
odoo_addons/hr_security/i18n/hr_security.pot
odoo_addons/hr_security/i18n/pt_BR.po
odoo_addons/hr_security/i18n/sl.po
odoo_addons/hr_security/security/hr_security.xml
odoo_addons/hr_security/security/ir.model.access.csv
odoo_addons/hr_security/security/ir_rule.xml
odoo_addons/hr_security/static/description/icon.png
odoo_addons/hr_security/views/hr_contract_view.xml
odoo_addons/hr_security/views/hr_employee_view.xml
